majormode/__init__.py
majormode/education.py
education_level_library-1.0.0.dist-info/LICENSE
education_level_library-1.0.0.dist-info/METADATA
education_level_library-1.0.0.dist-info/WHEEL
education_level_library-1.0.0.dist-info/top_level.txt
education_level_library-1.0.0.dist-info/RECORD
