Metadata-Version: 2.1
Name: education-level-library
Version: 1.0.0
Summary: Education Level Python Library
Home-page: UNKNOWN
Author: Daniel CAUNE
Author-email: daniel.caune@gmail.com
License: MIT
Project-URL: Bug Tracker, https://github.com/majormode/education-level-python-library/issues
Project-URL: Documentation, https://github.com/majormode/education-level-python-library
Project-URL: Source Code, https://github.com/majormode/education-level-python-library
Platform: any
Classifier: Development Status :: 5 - Production/Stable
Classifier: License :: OSI Approved :: MIT License
Classifier: Operating System :: OS Independent
Classifier: Programming Language :: Python
Classifier: Topic :: Software Development :: Libraries
Requires-Python: >=3
License-File: LICENSE
Requires-Dist: pipfile
Requires-Dist: setuptools
Requires-Dist: wheel
Requires-Dist: twine
